flask_APIAuth/__init__.py
flask_APIAuth/__version__.py
flask_APIAuth/core.py
Flask_APIAuth-0.1.1.dist-info/LICENSE
Flask_APIAuth-0.1.1.dist-info/METADATA
Flask_APIAuth-0.1.1.dist-info/WHEEL
Flask_APIAuth-0.1.1.dist-info/top_level.txt
Flask_APIAuth-0.1.1.dist-info/RECORD
