Metadata-Version: 2.1
Name: Flask-APIAuth
Version: 0.1.1
Summary: flask api auth modules.
Home-page: https://gitee.com/minuy/Flask-APIAuth
Author: Minuy
Author-email: y17mmz@live.com
License: MIT
Platform: UNKNOWN
Classifier: License :: OSI Approved :: MIT License
Classifier: Programming Language :: Python
Classifier: Programming Language :: Python :: 3
Classifier: Programming Language :: Python :: 3.8
Classifier: Programming Language :: Python :: Implementation :: CPython
Classifier: Programming Language :: Python :: Implementation :: PyPy
Requires: flask
Requires-Python: >=3.8.1
